Metadata-Version: 2.1
Name: deka-plog
Version: 1.2.4
Summary: Output logs to console and files
Author: zy
Author-email: 517826265@qq.com
